pubmed_server.py
pubmed_web_search.py
uh_joan_pubmed_mcp_server-0.1.4.dist-info/METADATA
uh_joan_pubmed_mcp_server-0.1.4.dist-info/WHEEL
uh_joan_pubmed_mcp_server-0.1.4.dist-info/entry_points.txt
uh_joan_pubmed_mcp_server-0.1.4.dist-info/licenses/LICENSE
uh_joan_pubmed_mcp_server-0.1.4.dist-info/RECORD
