Metadata-Version: 2.4
Name: uh-joan-pubmed-mcp-server
Version: 0.1.4
Summary: An MCP server for searching, retrieving, and analyzing articles from PubMed
Project-URL: Homepage, https://github.com/uh-joan/pubmed-mcp-server
Project-URL: Documentation, https://github.com/uh-joan/pubmed-mcp-server#readme
Project-URL: Repository, https://github.com/uh-joan/pubmed-mcp-server
Project-URL: Bug Tracker, https://github.com/uh-joan/pubmed-mcp-server/issues
License: MIT
License-File: LICENSE
Keywords: articles,biomedical,mcp,pubmed,research,search
Classifier: Development Status :: 4 - Beta
Classifier: Intended Audience :: Developers
Classifier: Intended Audience :: Science/Research
Classifier: License :: OSI Approved :: MIT License
Classifier: Operating System :: OS Independent
Classifier: Programming Language :: Python :: 3
Classifier: Programming Language :: Python :: 3.10
Classifier: Programming Language :: Python :: 3.11
Classifier: Programming Language :: Python :: 3.12
Classifier: Programming Language :: Python :: 3.13
Classifier: Topic :: Internet :: WWW/HTTP :: Dynamic Content
Classifier: Topic :: Scientific/Engineering :: Bio-Informatics
Classifier: Topic :: Scientific/Engineering :: Information Analysis
Classifier: Topic :: Software Development :: Libraries :: Python Modules
Requires-Python: >=3.10
Requires-Dist: beautifulsoup4>=4.9.3
Requires-Dist: httpx>=0.27.0
Requires-Dist: mcp>=1.4.1
Requires-Dist: requests>=2.25.1
